opensampl/__init__.py
opensampl/cli.py
opensampl/load_data.py
opensampl/metrics.py
opensampl/references.py
opensampl/collect/__init__.py
opensampl/collect/cli.py
opensampl/collect/modem.py
opensampl/collect/microchip/__init__.py
opensampl/collect/microchip/tp4100/__init__.py
opensampl/collect/microchip/tp4100/collect_4100.py
opensampl/collect/microchip/twst/__init__.py
opensampl/collect/microchip/twst/context.py
opensampl/collect/microchip/twst/generate_twst_files.py
opensampl/collect/microchip/twst/readings.py
opensampl/config/__init__.py
opensampl/config/base.py
opensampl/config/server.py
opensampl/config/tp4100.py
opensampl/create/__init__.py
opensampl/create/create_vendor.py
opensampl/create/insert_markers.py
opensampl/db/__init__.py
opensampl/db/access_orm.py
opensampl/db/orm.py
opensampl/helpers/__init__.py
opensampl/load/__init__.py
opensampl/load/data.py
opensampl/load/routing.py
opensampl/load/table_factory.py
opensampl/server/__init__.py
opensampl/server/cli.py
opensampl/server/cli2.py
opensampl/server/default.env
opensampl/server/docker-compose.yaml
opensampl/server/grafana/Dockerfile
opensampl/server/grafana/grafana.env
opensampl/server/grafana/grafana-dashboards/public-timing-dashboard.json
opensampl/server/grafana/grafana-dashboards/public_twst_dash.json
opensampl/server/grafana/grafana-dashboards/timing-dashboard2.json
opensampl/server/grafana/grafana-dashboards/twst_dash.json
opensampl/server/grafana/grafana-provisioning/dashboards/dashboard.yaml
opensampl/server/grafana/grafana-provisioning/datasources/postgresql.yaml
opensampl/vendors/__init__.py
opensampl/vendors/adva.py
opensampl/vendors/base_probe.py
opensampl/vendors/constants.py
opensampl/vendors/microchip/__init__.py
opensampl/vendors/microchip/tp4100.py
opensampl/vendors/microchip/twst.py
opensampl-1.1.5.dist-info/METADATA
opensampl-1.1.5.dist-info/WHEEL
opensampl-1.1.5.dist-info/entry_points.txt
opensampl-1.1.5.dist-info/licenses/LICENSE
opensampl-1.1.5.dist-info/RECORD
