Metadata-Version: 2.4
Name: opensampl
Version: 1.1.5
Summary: Python tools for adding clock data to a timescale db.
Project-URL: Homepage, https://github.com/ORNL/OpenSAMPL
Project-URL: Repository, https://github.com/ORNL/OpenSAMPL
Project-URL: Documentation, https://ornl.github.io/OpenSAMPL
Project-URL: Changelog, https://github.com/ORNL/OpenSAMPL/blob/main/CHANGELOG.md
Author-email: Midgie MacFarland <macfarlandmj@ornl.gov>, Cory Watson <watsoncl1@ornl.gov>, Joshua Grant <grantjn@ornl.gov>
License: MIT License
License-File: LICENSE
Classifier: Development Status :: 3 - Alpha
Classifier: Environment :: Console
Classifier: Environment :: Web Environment
Classifier: Framework :: Pydantic
Classifier: Framework :: Pydantic :: 2
Classifier: Intended Audience :: Developers
Classifier: Intended Audience :: Science/Research
Classifier: Intended Audience :: System Administrators
Classifier: Intended Audience :: Telecommunications Industry
Classifier: License :: OSI Approved :: MIT License
Classifier: Natural Language :: English
Classifier: Operating System :: OS Independent
Classifier: Programming Language :: Python :: 3
Classifier: Programming Language :: Python :: 3.9
Classifier: Programming Language :: Python :: 3.10
Classifier: Programming Language :: Python :: 3.11
Classifier: Programming Language :: Python :: 3.12
Classifier: Topic :: Communications
Classifier: Topic :: Database
Classifier: Topic :: Database :: Database Engines/Servers
Classifier: Topic :: Scientific/Engineering
Classifier: Topic :: Scientific/Engineering :: Physics
Classifier: Topic :: Scientific/Engineering :: Visualization
Classifier: Topic :: Software Development :: Libraries :: Python Modules
Classifier: Topic :: System :: Monitoring
Classifier: Topic :: System :: Networking :: Monitoring
Requires-Python: <3.13,>=3.9
Requires-Dist: allantools
Requires-Dist: astor
Requires-Dist: click<9,>=8.0.0
Requires-Dist: geoalchemy2==0.16.0
Requires-Dist: jinja2>=3.1.6
Requires-Dist: libcst
Requires-Dist: loguru<0.8,>=0.7.0
Requires-Dist: numpy<2,>=1.26.4
Requires-Dist: pandas<3,>=2.2.1
Requires-Dist: psycopg2-binary<3,>=2.9.0
Requires-Dist: pydantic-settings>=2.9.0
Requires-Dist: pydantic<3,>=2.10.3
Requires-Dist: python-dotenv
Requires-Dist: python-multipart<0.0.21,>=0.0.20
Requires-Dist: pytz~=2024.1
Requires-Dist: pyyaml<7,>=6.0.0
Requires-Dist: requests<3,>=2.31.0
Requires-Dist: sqlalchemy<3,>=2.0.39
Requires-Dist: tabulate
Requires-Dist: tqdm<5,>=4.66.2
Provides-Extra: collect
Requires-Dist: telnetlib3==2.0.4; extra == 'collect'
Provides-Extra: server
